py-jdb/__init__.py
py-jdb/json_db_handle.py
py-jdb/log_handle.py
py-jdb/util_utils.py
python-jdb/__init__.py
python-jdb/json_db_handle.py
python-jdb/log_handle.py
python-jdb/util_utils.py
pythonjdb/__init__.py
pythonjdb/json_db_handle.py
pythonjdb/log_handle.py
pythonjdb/util_utils.py
python_jdb-0.1.1.dist-info/LICENSE
python_jdb-0.1.1.dist-info/METADATA
python_jdb-0.1.1.dist-info/WHEEL
python_jdb-0.1.1.dist-info/top_level.txt
python_jdb-0.1.1.dist-info/RECORD
